<?xml version="1.0" encoding="utf-8"?><toc><breadcrumbs><li><a href="2334e687-57a6-4a54-a730-9a0a8f438ea0.htm">Docs</a></li><li><a href="7f278c22-7484-6fde-6d80-89b88d6b88ed.htm">Word<wbr />Hidden<wbr />Powers.<wbr />Repositories</a></li><li><a href="526857a8-e380-5ec5-28fd-f745fb60d97e.htm">Repository<wbr />Data<wbr />Set.<wbr />Decimal<wbr />Powers<wbr />Data<wbr />Table</a></li></breadcrumbs><tocItems><li><a id="1884146b-6adb-19f3-d61a-8427d5b3a0aa" class="has-submenu" href="1884146b-6adb-19f3-d61a-8427d5b3a0aa.htm"><span data-tocFile="../toc/IDAJ0CB0.xml" class="icon toggle" onclick="ToggleExpandCollapse(this); return false;"><i class="fa fa-angle-right"> </i></span>конструкторы</a><ul class="toc-menu is-hidden"> </ul></li><li><a id="9a69658a-7bb0-e784-0a3d-4f8c38e031ef" class="has-submenu" href="9a69658a-7bb0-e784-0a3d-4f8c38e031ef.htm"><span data-tocFile="../toc/IDBJ0CB0.xml" class="icon toggle" onclick="ToggleExpandCollapse(this); return false;"><i class="fa fa-angle-right"> </i></span>свойства</a><ul class="toc-menu is-hidden"> </ul></li><li><a id="1e89d9e0-af3d-5c7a-87cd-5bc49306ded4" class="has-submenu" href="1e89d9e0-af3d-5c7a-87cd-5bc49306ded4.htm"><span data-tocFile="../toc/IDCJ0CB0.xml" class="icon toggle" onclick="ToggleExpandCollapse(this); return false;"><i class="fa fa-angle-right"> </i></span>методы</a><ul class="toc-menu is-hidden"> </ul></li><li><a id="76642793-3788-e04b-75e6-942cf531eb0f" class="has-submenu" href="76642793-3788-e04b-75e6-942cf531eb0f.htm"><span data-tocFile="../toc/IDDJ0CB0.xml" class="icon toggle" onclick="ToggleExpandCollapse(this); return false;"><i class="fa fa-angle-right"> </i></span>события</a><ul class="toc-menu is-hidden"> </ul></li><li><a id="263c897c-f73e-b0b7-b752-e0b98e25f79e" href="263c897c-f73e-b0b7-b752-e0b98e25f79e.htm">поля</a></li></tocItems></toc>