<?xml version="1.0" encoding="utf-8"?><toc><breadcrumbs><li><a href="2334e687-57a6-4a54-a730-9a0a8f438ea0.htm">Docs</a></li><li><a href="b6d43161-01ee-4617-ea1f-06bfa3dd67df.htm">Control<wbr />Library.<wbr />Controls.<wbr />QRCoder</a></li><li><a href="8f4d2222-44aa-8e64-e82c-da7b5368ca0b.htm">Postscript<wbr />QRCode</a></li><li><a href="af09f353-f4e0-080c-82a7-1e059b1fad48.htm">методы</a></li></breadcrumbs><tocItems><li><a id="68204cb8-ddd1-ae40-f76c-ae63caa68ce9" class="has-submenu" href="68204cb8-ddd1-ae40-f76c-ae63caa68ce9.htm"><span data-tocFile="../toc/IDAC0FB0H.xml" class="icon toggle" onclick="ToggleExpandCollapse(this); return false;"><i class="fa fa-angle-right"> </i></span>Get<wbr />Graphic</a><ul class="toc-menu is-hidden"> </ul></li></tocItems></toc>